design_m.v
//personal encoder

module compression(
    input i_clk,
    input c14,
    //input wire[15:0] i_bits,
    output wire[7:0] o_bits
);
//intermdiate wires 
wire[15:0] k_add_out;
wire[2:0] p_out_;
wire[3:0]  lsls_out_;


wire ack;
wire[15:0] add_in;
wire[15:0] add_out;
wire[2:0] p_out;
wire[3:0] lsls_out;

//intermediate registers
reg[15:0] pcm_data; //have to give it some initial value
reg[15:0] r_add_in;
reg[15:0] r_add_out;
reg[2:0]  r_p_out = 0;
reg[3:0]  r_lsls_out = 0;
reg[7:0] r_out = 0;



//instantiatiate modules & all are combinational logic(pipelining into '4' stages)
k_bit_adder k_add_inst(.i_bits(add_in), .o_bits(k_add_out));
priority_encoder p_encoder_inst(.i_bits(add_out[14:5]), .o_bits(p_out_));
lsls_8  lsls_inst(.i_bits(k_add_out), .shift_bits(p_out), .o_bits(lsls_out_));


//with clock
uart_tx uart_tx_inst(.C14(c14), .i_clk(i_clk), .ack(ack), .data(pcm_data));

reg[2:0] lat_c = 0;
reg[1:0] state = 2'b00;
parameter idle = 2'b00;
parameter start = 2'b01;
always @(posedge i_clk) begin
    case(state) 
        idle: begin 
            if(ack == 1'b1) state <= start;
        end

        start: begin //assume all combinational takes one clock cycle..(latency = 3)
            r_add_in <= pcm_data;
            r_add_out <= k_add_out;
            r_p_out <= p_out_;
            r_lsls_out <= lsls_out_;

            if(lat_c != 4) lat_c = lat_c + 1;
            else begin 
                lat_c = 0;
                r_out =  {8{pcm_data[15]}}^{1'b0, p_out, lsls_out};
            end
            if(ack == 1'b0) state <= idle;
        end

    endcase

    
end
assign add_in = r_add_in;
assign add_out = r_add_out;
assign p_out   = r_p_out;
assign lsls_out = r_lsls_out;
//output:
assign o_bits = r_out;


endmodule


//zync-700 runs at 100MGHz, uart_bits
//baud rate: 115200, 8 bits : need to wait 868 cycles,
//I only care about C14(TX)
module uart_tx(
    input C14,
    input i_clk,
    output wire ack,
    output reg[15:0] data
);

initial begin 
data = 16'h000; //for the first value
end
reg r_ack = 0;
reg[1:0] state = 0;
reg[9:0] counter = 0;
reg[1:0] parts = 0;
reg[4:0] index= 0;
parameter idle   = 2'b00;
parameter start  = 2'b01;
parameter sample = 2'b10;
parameter stop   = 2'b11;



always @(posedge i_clk) begin 
    case(state)

    idle:begin 
        if(C14 == 1'b0) state <= start;
    end

    //goal sample in the middle
    start:begin 
        if(counter != 434) counter <= counter + 1;
        else begin 
            counter <= 0;
            state <= sample;
            r_ack <= 1'b0;  //new sample starting so have to restart;
        end
    end

    sample: begin 
        if(counter != 868) begin 
            counter <= counter + 1;
        end
        
        //sampling part
        //break it up
        else if(((index != 8) || (parts != 0)) && (index != 16)) begin 
            data[(15-index)] <= C14;
            index   <= index + 1;
            counter <= 0;
        end

        //will fail when index = 16, and index = 8 and parts = 0
        else begin
            state <= stop;
        end
        end
    
    stop: begin
        if(C14 == 1'b1) state <= idle;
        if(parts != 1) begin 
        parts <= parts + 1;//
        end
        else begin 
        parts <= 0;
        index <= 0;
        r_ack <= 1'b1;
        end
        counter <= 0;
    end

    endcase


end

assign ack = r_ack; //register is ready to read

endmodule


module priority_encoder(
    input wire[9:0] i_bits,
    output wire[2:0] o_bits
    //outputwire[7:0] bits_,
    //output wire im123_,
   // output wire im567_
);

reg[2:0] r_bits;
always@(*) begin 
    r_bits[0] = ((i_bits[0] | i_bits[1]) & ~(i_bits[2])) | (i_bits[3] & ~(i_bits[4])) | (i_bits[5] & ~i_bits[6]) | i_bits[9:7]; 
    r_bits[1] = ((i_bits[2] | i_bits[3]) & ~(i_bits[4]  | i_bits[5])) | (i_bits[9:7]);
    r_bits[2] = |(i_bits[9:4]);

end
assign o_bits = r_bits;
endmodule

lsls.v
module lsls_8(input wire[15:0] i_bits,
              input wire[2:0] shift_bits,
              output wire[3:0] o_bits );

integer i;
//intermediate wires aka "registers"
reg[15:0] layer1;
reg[15:0] layer2;
reg[15:0] layer3;
reg[15:0] layer4;
reg sel[3:0];



always @(*) begin 
//layer 1: aka shift 8
//calculating select line
sel[0] = shift_bits[0] & shift_bits[1] & shift_bits[2];

for(i = 0; i < 16; i = i+1) begin 
    if(i < 8) layer1[i] = (~sel[0]  & i_bits[i]) | (sel[0] & i_bits[i+8]);

    else layer1[i] = (~sel[0] & i_bits[i]);
    
end

//layer 2: aka shift 4
sel[1] = shift_bits[2] ^ (shift_bits[1] & shift_bits[0]);
for(i = 0; i < 16; i = i + 1) begin 
    if( i < 13) layer2[i] = sel[1] ? layer1[i+4] : layer1[i];

    else layer2[i] = sel[1] ? 0 : layer1[i]; 

end 


//layer 3: aka shift 2
sel[2] = shift_bits[1] ^ shift_bits[0];
for(i = 0; i < 16; i = i+1) begin 
    if(i < 14)  layer3[i] = sel[2] ? layer2[i+2] : layer2[i];
    else        layer3[i] = sel[2] ? 0 : layer2[i];
end

//layer 4: aka shift 1
sel[3] = ~shift_bits[0];
for(i = 0 ; i < 16; i = i+1) begin 
    if(i < 15) layer4[i] = sel[3] ? layer3[i+1] : layer3[i];
    else layer4[i] = sel[3] ? 0 : layer3[i];

end
end
assign o_bits = layer4[3:0];
endmodule

k_16bit_1.v
module k_bit_adder(input wire[15:0] i_bits,
                output  reg[15:0] Gen,  //monitoring purposes
                output wire[15:0] o_bits);

//output "register"
reg[15:0] r_bits;

//intermediate  wires aka 'reg'
reg[15:0] im1;
reg        c0; //carry bit
reg        G0; //generation bit 0


//propogation values
reg[15:0] prop_1; 
reg[15:0] prop_2;
reg[15:0] prop_3; 
reg[15:0] prop_4;

//generation values

//extra declaration
integer i;

//pure combinational logic
always @(*)
begin 
    c0  = i_bits[15];
    im1 = {16{i_bits[15]}} ^ i_bits;//xor all bits with MSB


    //koggestone! Depth "pre-proccesing"
    Gen[0] = im1[0] & c0;

    //layer:1   (S0, S1)
    r_bits[0] = c0 ^ im1[0];
    
    prop_1[0] = c0 ^ im1[0]; //special cases
    prop_1[1] = (c0 ^ im1[0]) & im1[1];
    for(i = 2 ; i <= 15 ;i = i + 1)   
    begin 
        prop_1[i] = im1[i] & im1[i-1]; 
    end

    Gen[1] = Gen[0] & im1[1];

    //carrying the propogation line(b0)
    prop_1[0] = c0 ^ im1[0];
 
    


    //layer:2   (S2, S3)
    for(i = 2; i <= 15 ; i = i + 1) begin 
        prop_2[i] = prop_1[i] & prop_1[i-2]; 
    end


    Gen[2] = Gen[0] & prop_1[2];
    Gen[3] = Gen[1] & prop_1[3];

    //carrying previous propogation(b1, b2)
    prop_2[0] = prop_1[0];
    prop_2[1] = prop_1[1];
   

//layer 3:
for( i = 4; i <= 15; i = i+1) begin 
    prop_3[i] = prop_2[i] & prop_2[i-4];
end
    //generation bit G4-G7
    Gen[4] = Gen[0] & prop_2[4];
    Gen[5] = Gen[1] & prop_2[5];
    Gen[6] = Gen[2] & prop_2[6];
    Gen[7] = Gen[3] & prop_2[7];
    

    //carrying previous propogation(b0,b1,b2,b3)
    prop_3[0] = prop_2[0];
    prop_3[1] = prop_2[1];
    prop_3[2] = prop_2[2];
    prop_3[3] = prop_2[3];


//layer 4:
    for(i = 8; i <= 15; i = i +1)begin 
        prop_4[i] = prop_3[i-8]  & prop_3[i];
    end

    for(i = 8; i <= 15; i = i+1) begin
        Gen[i] = Gen[i-8] & prop_3[i]; 
    end

    //previous propgation(b0-b7)
    for(i = 0; i< 8; i = i +1)begin 
        prop_4[i] = prop_3[i];
    end

    //post proccessing for rest of bits 
    for(i = 1; i <= 15; i = i+1) begin 
        r_bits[i] = im1[i] ^ Gen[i-1]; //origial propgate bit.
    end


end

assign o_bits = r_bits; 
endmodule

design_tb.v

`timescale 1ns/1ps

// //when making a testbech inputs = registers;
// module tb_design;
// reg[15:0] i_bits;
// wire[15:0] o_bits;
// reg[15:0] gen_bits;


// k_bit_adder uut(.i_bits(i_bits), .Gen(gen_bits),.o_bits(o_bits));
// initial begin

// $display("Time\tinput_bits\toutput_bits\tgen_bits");
// $monitor("%0t\t%h\t\t%b\t\t%b", $time, i_bits, o_bits, gen_bits);

// //test some edgecases

// //i_bits = 16'hF001; #10;
// //i_bits = 16'hFFFF; #10;
// $finish;

// end

// endmodule;



//testing left shit module
// module lsls_v;
// reg[15:0] abs_val;
// reg[2:0] shift_b;
// wire[3:0] o_bits;

// lsls_8 uut(.i_bits(abs_val), .shift_bits(shift_b), .o_bits(o_bits));
// initial begin
//     $display("input\tshift\toutput");
//     $monitor("%b\t%b\t%b", abs_val, shift_b, o_bits);

//     abs_val = 16'h000F; shift_b = 3 'b001;  #10;
//     abs_val = 16'h0FF0; shift_b = 3'b001; #10;
//     abs_val = 16'hFFC0; shift_b = 3'b101; #10;
//     $finish;
// end


// endmodule

module compression_tb;

reg i_clk;
reg c14;
wire[7:0] o_bits;

//always #10 nanoseconds = 100 MGHZ
reg [7:0] data_sequence [0:1]; // two sequences
initial i_clk = 1'b1;
always  #10 i_clk = ~i_clk;   //dump into file //1 clock cyles is (20 ns is one clockcyle)
compression uut(.i_clk(i_clk),.c14(c14),.o_bits(o_bits));
integer i,j;
initial begin
    $dumpfile("compression.vcd");
    $dumpvars(0, compression_tb);
    data_sequence[0] = 8'b10100101; 
    data_sequence[1] = 8'b10100101; 

    for (i = 0; i < 2; i = i + 1) begin
        c14 = 1'b0;
        #(8680*2); //hold for one clock cycle
        for (j = 7; j >= 0; j = j - 1) begin
            c14 = data_sequence[i][j];
            #(8680*2); 
        end
        // Stop condition (c14 = 1)
        c14 = 1'b1;
        #(8680*2);
    end
   #100; //10 clockcyles should finish by then! 
$finish;
end


endmodule

compression.vcd
$date
	Fri Mar 27 15:37:13 2026
$end
$version
	Icarus Verilog
$end
$timescale
	1ps
$end
$scope module compression_tb $end
$var wire 8 ! o_bits [7:0] $end
$var reg 1 " c14 $end
$var reg 1 # i_clk $end
$var integer 32 $ i [31:0] $end
$var integer 32 % j [31:0] $end
$scope module uut $end
$var wire 16 & add_in [15:0] $end
$var wire 1 " c14 $end
$var wire 1 # i_clk $end
$var wire 4 ' lsls_out [3:0] $end
$var wire 8 ( o_bits [7:0] $end
$var wire 3 ) p_out [2:0] $end
$var wire 16 * pcm_data [15:0] $end
$var wire 3 + p_out_ [2:0] $end
$var wire 4 , lsls_out_ [3:0] $end
$var wire 16 - k_add_out [15:0] $end
$var wire 16 . add_out [15:0] $end
$var wire 1 / ack $end
$var parameter 2 0 idle $end
$var parameter 2 1 start $end
$var reg 3 2 lat_c [2:0] $end
$var reg 16 3 r_add_in [15:0] $end
$var reg 16 4 r_add_out [15:0] $end
$var reg 4 5 r_lsls_out [3:0] $end
$var reg 8 6 r_out [7:0] $end
$var reg 3 7 r_p_out [2:0] $end
$var reg 2 8 state [1:0] $end
$scope module k_add_inst $end
$var wire 16 9 i_bits [15:0] $end
$var wire 16 : o_bits [15:0] $end
$var reg 16 ; Gen [15:0] $end
$var reg 1 < c0 $end
$var reg 16 = im1 [15:0] $end
$var reg 16 > prop_1 [15:0] $end
$var reg 16 ? prop_2 [15:0] $end
$var reg 16 @ prop_3 [15:0] $end
$var reg 16 A prop_4 [15:0] $end
$var reg 16 B r_bits [15:0] $end
$var integer 32 C i [31:0] $end
$upscope $end
$scope module lsls_inst $end
$var wire 16 D i_bits [15:0] $end
$var wire 3 E shift_bits [2:0] $end
$var wire 4 F o_bits [3:0] $end
$var reg 16 G layer1 [15:0] $end
$var reg 16 H layer2 [15:0] $end
$var reg 16 I layer3 [15:0] $end
$var reg 16 J layer4 [15:0] $end
$var integer 32 K i [31:0] $end
$upscope $end
$scope module p_encoder_inst $end
$var wire 10 L i_bits [9:0] $end
$var wire 3 M o_bits [2:0] $end
$var reg 3 N r_bits [2:0] $end
$upscope $end
$scope module uart_tx_inst $end
$var wire 1 " C14 $end
$var wire 1 / ack $end
$var wire 1 # i_clk $end
$var parameter 2 O idle $end
$var parameter 2 P sample $end
$var parameter 2 Q start $end
$var parameter 2 R stop $end
$var reg 10 S counter [9:0] $end
$var reg 16 T data [15:0] $end
$var reg 5 U index [4:0] $end
$var reg 2 V parts [1:0] $end
$var reg 1 W r_ack $end
$var reg 2 X state [1:0] $end
$upscope $end
$upscope $end
$upscope $end
$enddefinitions $end
$comment Show the parameter values. $end
$dumpall
b11 R
b1 Q
b10 P
b0 O
b1 1
b0 0
$end
#0
$dumpvars
b1 X
0W
b0 V
b0 U
b0 T
b0 S
bx N
bx M
bx L
bx K
bx J
bx I
bx H
bx G
bx F
b0 E
bx D
bx C
bx B
bx A
bx @
bx ?
bx >
bx =
x<
bx ;
bx :
bx 9
b0 8
b0 7
b0 6
b0 5
bx 4
bx 3
b0 2
0/
bx .
bx -
bx ,
bx +
b0 *
b0 )
b0 (
b0 '
bx &
bx %
b0 $
1#
0"
b0 !
$end
#10000
0#
#20000
b1 S
1#
#30000
0#
#40000
b10 S
1#
#50000
0#
#60000
b11 S
1#
#70000
0#
#80000
b100 S
1#
#90000
0#
#100000
b101 S
1#
#110000
0#
#120000
b110 S
1#
#130000
0#
#140000
b111 S
1#
#150000
0#
#160000
b1000 S
1#
#170000
0#
#180000
b1001 S
1#
#190000
0#
#200000
b1010 S
1#
#210000
0#
#220000
b1011 S
1#
#230000
0#
#240000
b1100 S
1#
#250000
0#
#260000
b1101 S
1#
#270000
0#
#280000
b1110 S
1#
#290000
0#
#300000
b1111 S
1#
#310000
0#
#320000
b10000 S
1#
#330000
0#
#340000
b10001 S
1#
#350000
0#
#360000
b10010 S
1#
#370000
0#
#380000
b10011 S
1#
#390000
0#
#400000
b10100 S
1#
#410000
0#
#420000
b10101 S
1#
#430000
0#
#440000
b10110 S
1#
#450000
0#
#460000
b10111 S
1#
#470000
0#
#480000
b11000 S
1#
#490000
0#
#500000
b11001 S
1#
#510000
0#
#520000
b11010 S
1#
#530000
0#
#540000
b11011 S
1#
#550000
0#
#560000
b11100 S
1#
#570000
0#
#580000
b11101 S
1#
#590000
0#
#600000
b11110 S
1#
#610000
0#
#620000
b11111 S
1#
#630000
0#
#640000
b100000 S
1#
#650000
0#
#660000
b100001 S
1#
#670000
0#
#680000
b100010 S
1#
#690000
0#
#700000
b100011 S
1#
#710000
0#
#720000
b100100 S
1#
#730000
0#
#740000
b100101 S
1#
#750000
0#
#760000
b100110 S
1#
#770000
0#
#780000
b100111 S
1#
#790000
0#
#800000
b101000 S
1#
#810000
0#
#820000
b101001 S
1#
#830000
0#
#840000
b101010 S
1#
#850000
0#
#860000
b101011 S
1#
#870000
0#
#880000
b101100 S
1#
#890000
0#
#900000
b101101 S
1#
#910000
0#
#920000
b101110 S
1#
#930000
0#
#940000
b101111 S
1#
#950000
0#
#960000
b110000 S
1#
#970000
0#
#980000
b110001 S
1#
#990000
0#
#1000000
b110010 S
1#
#1010000
0#
#1020000
b110011 S
1#
#1030000
0#
#1040000
b110100 S
1#
#1050000
0#
#1060000
b110101 S
1#
#1070000
0#
#1080000
b110110 S
1#
#1090000
0#
#1100000
b110111 S
1#
#1110000
0#
#1120000
b111000 S
1#
#1130000
0#
#1140000
b111001 S
1#
#1150000
0#
#1160000
b111010 S
1#
#1170000
0#
#1180000
b111011 S
1#
#1190000
0#
#1200000
b111100 S
1#
#1210000
0#
#1220000
b111101 S
1#
#1230000
0#
#1240000
b111110 S
1#
#1250000
0#
#1260000
b111111 S
1#
#1270000
0#
#1280000
b1000000 S
1#
#1290000
0#
#1300000
b1000001 S
1#
#1310000
0#
#1320000
b1000010 S
1#
#1330000
0#
#1340000
b1000011 S
1#
#1350000
0#
#1360000
b1000100 S
1#
#1370000
0#
#1380000
b1000101 S
1#
#1390000
0#
#1400000
b1000110 S
1#
#1410000
0#
#1420000
b1000111 S
1#
#1430000
0#
#1440000
b1001000 S
1#
#1450000
0#
#1460000
b1001001 S
1#
#1470000
0#
#1480000
b1001010 S
1#
#1490000
0#
#1500000
b1001011 S
1#
#1510000
0#
#1520000
b1001100 S
1#
#1530000
0#
#1540000
b1001101 S
1#
#1550000
0#
#1560000
b1001110 S
1#
#1570000
0#
#1580000
b1001111 S
1#
#1590000
0#
#1600000
b1010000 S
1#
#1610000
0#
#1620000
b1010001 S
1#
#1630000
0#
#1640000
b1010010 S
1#
#1650000
0#
#1660000
b1010011 S
1#
#1670000
0#
#1680000
b1010100 S
1#
#1690000
0#
#1700000
b1010101 S
1#
#1710000
0#
#1720000
b1010110 S
1#
#1730000
0#
#1740000
b1010111 S
1#
#1750000
0#
#1760000
b1011000 S
1#
#1770000
0#
#1780000
b1011001 S
1#
#1790000
0#
#1800000
b1011010 S
1#
#1810000
0#
#1820000
b1011011 S
1#
#1830000
0#
#1840000
b1011100 S
1#
#1850000
0#
#1860000
b1011101 S
1#
#1870000
0#
#1880000
b1011110 S
1#
#1890000
0#
#1900000
b1011111 S
1#
#1910000
0#
#1920000
b1100000 S
1#
#1930000
0#
#1940000
b1100001 S
1#
#1950000
0#
#1960000
b1100010 S
1#
#1970000
0#
#1980000
b1100011 S
1#
#1990000
0#
#2000000
b1100100 S
1#
#2010000
0#
#2020000
b1100101 S
1#
#2030000
0#
#2040000
b1100110 S
1#
#2050000
0#
#2060000
b1100111 S
1#
#2070000
0#
#2080000
b1101000 S
1#
#2090000
0#
#2100000
b1101001 S
1#
#2110000
0#
#2120000
b1101010 S
1#
#2130000
0#
#2140000
b1101011 S
1#
#2150000
0#
#2160000
b1101100 S
1#
#2170000
0#
#2180000
b1101101 S
1#
#2190000
0#
#2200000
b1101110 S
1#
#2210000
0#
#2220000
b1101111 S
1#
#2230000
0#
#2240000
b1110000 S
1#
#2250000
0#
#2260000
b1110001 S
1#
#2270000
0#
#2280000
b1110010 S
1#
#2290000
0#
#2300000
b1110011 S
1#
#2310000
0#
#2320000
b1110100 S
1#
#2330000
0#
#2340000
b1110101 S
1#
#2350000
0#
#2360000
b1110110 S
1#
#2370000
0#
#2380000
b1110111 S
1#
#2390000
0#
#2400000
b1111000 S
1#
#2410000
0#
#2420000
b1111001 S
1#
#2430000
0#
#2440000
b1111010 S
1#
#2450000
0#
#2460000
b1111011 S
1#
#2470000
0#
#2480000
b1111100 S
1#
#2490000
0#
#2500000
b1111101 S
1#
#2510000
0#
#2520000
b1111110 S
1#
#2530000
0#
#2540000
b1111111 S
1#
#2550000
0#
#2560000
b10000000 S
1#
#2570000
0#
#2580000
b10000001 S
1#
#2590000
0#
#2600000
b10000010 S
1#
#2610000
0#
#2620000
b10000011 S
1#
#2630000
0#
#2640000
b10000100 S
1#
#2650000
0#
#2660000
b10000101 S
1#
#2670000
0#
#2680000
b10000110 S
1#
#2690000
0#
#2700000
b10000111 S
1#
#2710000
0#
#2720000
b10001000 S
1#
#2730000
0#
#2740000
b10001001 S
1#
#2750000
0#
#2760000
b10001010 S
1#
#2770000
0#
#2780000
b10001011 S
1#
#2790000
0#
#2800000
b10001100 S
1#
#2810000
0#
#2820000
b10001101 S
1#
#2830000
0#
#2840000
b10001110 S
1#
#2850000
0#
#2860000
b10001111 S
1#
#2870000
0#
#2880000
b10010000 S
1#
#2890000
0#
#2900000
b10010001 S
1#
#2910000
0#
#2920000
b10010010 S
1#
#2930000
0#
#2940000
b10010011 S
1#
#2950000
0#
#2960000
b10010100 S
1#
#2970000
0#
#2980000
b10010101 S
1#
#2990000
0#
#3000000
b10010110 S
1#
#3010000
0#
#3020000
b10010111 S
1#
#3030000
0#
#3040000
b10011000 S
1#
#3050000
0#
#3060000
b10011001 S
1#
#3070000
0#
#3080000
b10011010 S
1#
#3090000
0#
#3100000
b10011011 S
1#
#3110000
0#
#3120000
b10011100 S
1#
#3130000
0#
#3140000
b10011101 S
1#
#3150000
0#
#3160000
b10011110 S
1#
#3170000
0#
#3180000
b10011111 S
1#
#3190000
0#
#3200000
b10100000 S
1#
#3210000
0#
#3220000
b10100001 S
1#
#3230000
0#
#3240000
b10100010 S
1#
#3250000
0#
#3260000
b10100011 S
1#
#3270000
0#
#3280000
b10100100 S
1#
#3290000
0#
#3300000
b10100101 S
1#
#3310000
0#
#3320000
b10100110 S
1#
#3330000
0#
#3340000
b10100111 S
1#
#3350000
0#
#3360000
b10101000 S
1#
#3370000
0#
#3380000
b10101001 S
1#
#3390000
0#
#3400000
b10101010 S
1#
#3410000
0#
#3420000
b10101011 S
1#
#3430000
0#
#3440000
b10101100 S
1#
#3450000
0#
#3460000
b10101101 S
1#
#3470000
0#
#3480000
b10101110 S
1#
#3490000
0#
#3500000
b10101111 S
1#
#3510000
0#
#3520000
b10110000 S
1#
#3530000
0#
#3540000
b10110001 S
1#
#3550000
0#
#3560000
b10110010 S
1#
#3570000
0#
#3580000
b10110011 S
1#
#3590000
0#
#3600000
b10110100 S
1#
#3610000
0#
#3620000
b10110101 S
1#
#3630000
0#
#3640000
b10110110 S
1#
#3650000
0#
#3660000
b10110111 S
1#
#3670000
0#
#3680000
b10111000 S
1#
#3690000
0#
#3700000
b10111001 S
1#
#3710000
0#
#3720000
b10111010 S
1#
#3730000
0#
#3740000
b10111011 S
1#
#3750000
0#
#3760000
b10111100 S
1#
#3770000
0#
#3780000
b10111101 S
1#
#3790000
0#
#3800000
b10111110 S
1#
#3810000
0#
#3820000
b10111111 S
1#
#3830000
0#
#3840000
b11000000 S
1#
#3850000
0#
#3860000
b11000001 S
1#
#3870000
0#
#3880000
b11000010 S
1#
#3890000
0#
#3900000
b11000011 S
1#
#3910000
0#
#3920000
b11000100 S
1#
#3930000
0#
#3940000
b11000101 S
1#
#3950000
0#
#3960000
b11000110 S
1#
#3970000
0#
#3980000
b11000111 S
1#
#3990000
0#
#4000000
b11001000 S
1#
#4010000
0#
#4020000
b11001001 S
1#
#4030000
0#
#4040000
b11001010 S
1#
#4050000
0#
#4060000
b11001011 S
1#
#4070000
0#
#4080000
b11001100 S
1#
#4090000
0#
#4100000
b11001101 S
1#
#4110000
0#
#4120000
b11001110 S
1#
#4130000
0#
#4140000
b11001111 S
1#
#4150000
0#
#4160000
b11010000 S
1#
#4170000
0#
#4180000
b11010001 S
1#
#4190000
0#
#4200000
b11010010 S
1#
#4210000
0#
#4220000
b11010011 S
1#
#4230000
0#
#4240000
b11010100 S
1#
#4250000
0#
#4260000
b11010101 S
1#
#4270000
0#
#4280000
b11010110 S
1#
#4290000
0#
#4300000
b11010111 S
1#
#4310000
0#
#4320000
b11011000 S
1#
#4330000
0#
#4340000
b11011001 S
1#
#4350000
0#
#4360000
b11011010 S
1#
#4370000
0#
#4380000
b11011011 S
1#
#4390000
0#
#4400000
b11011100 S
1#
#4410000
0#
#4420000
b11011101 S
1#
#4430000
0#
#4440000
b11011110 S
1#
#4450000
0#
#4460000
b11011111 S
1#
#4470000
0#
#4480000
b11100000 S
1#
#4490000
0#
#4500000
b11100001 S
1#
#4510000
0#
#4520000
b11100010 S
1#
#4530000
0#
#4540000
b11100011 S
1#
#4550000
0#
#4560000
b11100100 S
1#
#4570000
0#
#4580000
b11100101 S
1#
#4590000
0#
#4600000
b11100110 S
1#
#4610000
0#
#4620000
b11100111 S
1#
#4630000
0#
#4640000
b11101000 S
1#
#4650000
0#
#4660000
b11101001 S
1#
#4670000
0#
#4680000
b11101010 S
1#
#4690000
0#
#4700000
b11101011 S
1#
#4710000
0#
#4720000
b11101100 S
1#
#4730000
0#
#4740000
b11101101 S
1#
#4750000
0#
#4760000
b11101110 S
1#
#4770000
0#
#4780000
b11101111 S
1#
#4790000
0#
#4800000
b11110000 S
1#
#4810000
0#
#4820000
b11110001 S
1#
#4830000
0#
#4840000
b11110010 S
1#
#4850000
0#
#4860000
b11110011 S
1#
#4870000
0#
#4880000
b11110100 S
1#
#4890000
0#
#4900000
b11110101 S
1#
#4910000
0#
#4920000
b11110110 S
1#
#4930000
0#
#4940000
b11110111 S
1#
#4950000
0#
#4960000
b11111000 S
1#
#4970000
0#
#4980000
b11111001 S
1#
#4990000
0#
#5000000
b11111010 S
1#
#5010000
0#
#5020000
b11111011 S
1#
#5030000
0#
#5040000
b11111100 S
1#
#5050000
0#
#5060000
b11111101 S
1#
#5070000
0#
#5080000
b11111110 S
1#
#5090000
0#
#5100000
b11111111 S
1#
#5110000
0#
#5120000
b100000000 S
1#
#5130000
0#
#5140000
b100000001 S
1#
#5150000
0#
#5160000
b100000010 S
1#
#5170000
0#
#5180000
b100000011 S
1#
#5190000
0#
#5200000
b100000100 S
1#
#5210000
0#
#5220000
b100000101 S
1#
#5230000
0#
#5240000
b100000110 S
1#
#5250000
0#
#5260000
b100000111 S
1#
#5270000
0#
#5280000
b100001000 S
1#
#5290000
0#
#5300000
b100001001 S
1#
#5310000
0#
#5320000
b100001010 S
1#
#5330000
0#
#5340000
b100001011 S
1#
#5350000
0#
#5360000
b100001100 S
1#
#5370000
0#
#5380000
b100001101 S
1#
#5390000
0#
#5400000
b100001110 S
1#
#5410000
0#
#5420000
b100001111 S
1#
#5430000
0#
#5440000
b100010000 S
1#
#5450000
0#
#5460000
b100010001 S
1#
#5470000
0#
#5480000
b100010010 S
1#
#5490000
0#
#5500000
b100010011 S
1#
#5510000
0#
#5520000
b100010100 S
1#
#5530000
0#
#5540000
b100010101 S
1#
#5550000
0#
#5560000
b100010110 S
1#
#5570000
0#
#5580000
b100010111 S
1#
#5590000
0#
#5600000
b100011000 S
1#
#5610000
0#
#5620000
b100011001 S
1#
#5630000
0#
#5640000
b100011010 S
1#
#5650000
0#
#5660000
b100011011 S
1#
#5670000
0#
#5680000
b100011100 S
1#
#5690000
0#
#5700000
b100011101 S
1#
#5710000
0#
#5720000
b100011110 S
1#
#5730000
0#
#5740000
b100011111 S
1#
#5750000
0#
#5760000
b100100000 S
1#
#5770000
0#
#5780000
b100100001 S
1#
#5790000
0#
#5800000
b100100010 S
1#
#5810000
0#
#5820000
b100100011 S
1#
#5830000
0#
#5840000
b100100100 S
1#
#5850000
0#
#5860000
b100100101 S
1#
#5870000
0#
#5880000
b100100110 S
1#
#5890000
0#
#5900000
b100100111 S
1#
#5910000
0#
#5920000
b100101000 S
1#
#5930000
0#
#5940000
b100101001 S
1#
#5950000
0#
#5960000
b100101010 S
1#
#5970000
0#
#5980000
b100101011 S
1#
#5990000
0#
#6000000
b100101100 S
1#
#6010000
0#
#6020000
b100101101 S
1#
#6030000
0#
#6040000
b100101110 S
1#
#6050000
0#
#6060000
b100101111 S
1#
#6070000
0#
#6080000
b100110000 S
1#
#6090000
0#
#6100000
b100110001 S
1#
#6110000
0#
#6120000
b100110010 S
1#
#6130000
0#
#6140000
b100110011 S
1#
#6150000
0#
#6160000
b100110100 S
1#
#6170000
0#
#6180000
b100110101 S
1#
#6190000
0#
#6200000
b100110110 S
1#
#6210000
0#
#6220000
b100110111 S
1#
#6230000
0#
#6240000
b100111000 S
1#
#6250000
0#
#6260000
b100111001 S
1#
#6270000
0#
#6280000
b100111010 S
1#
#6290000
0#
#6300000
b100111011 S
1#
#6310000
0#
#6320000
b100111100 S
1#
#6330000
0#
#6340000
b100111101 S
1#
#6350000
0#
#6360000
b100111110 S
1#
#6370000
0#
#6380000
b100111111 S
1#
#6390000
0#
#6400000
b101000000 S
1#
#6410000
0#
#6420000
b101000001 S
1#
#6430000
0#
#6440000
b101000010 S
1#
#6450000
0#
#6460000
b101000011 S
1#
#6470000
0#
#6480000
b101000100 S
1#
#6490000
0#
#6500000
b101000101 S
1#
#6510000
0#
#6520000
b101000110 S
1#
#6530000
0#
#6540000
b101000111 S
1#
#6550000
0#
#6560000
b101001000 S
1#
#6570000
0#
#6580000
b101001001 S
1#
#6590000
0#
#6600000
b101001010 S
1#
#6610000
0#
#6620000
b101001011 S
1#
#6630000
0#
#6640000
b101001100 S
1#
#6650000
0#
#6660000
b101001101 S
1#
#6670000
0#
#6680000
b101001110 S
1#
#6690000
0#
#6700000
b101001111 S
1#
#6710000
0#
#6720000
b101010000 S
1#
#6730000
0#
#6740000
b101010001 S
1#
#6750000
0#
#6760000
b101010010 S
1#
#6770000
0#
#6780000
b101010011 S
1#
#6790000
0#
#6800000
b101010100 S
1#
#6810000
0#
#6820000
b101010101 S
1#
#6830000
0#
#6840000
b101010110 S
1#
#6850000
0#
#6860000
b101010111 S
1#
#6870000
0#
#6880000
b101011000 S
1#
#6890000
0#
#6900000
b101011001 S
1#
#6910000
0#
#6920000
b101011010 S
1#
#6930000
0#
#6940000
b101011011 S
1#
#6950000
0#
#6960000
b101011100 S
1#
#6970000
0#
#6980000
b101011101 S
1#
#6990000
0#
#7000000
b101011110 S
1#
#7010000
0#
#7020000
b101011111 S
1#
#7030000
0#
#7040000
b101100000 S
1#
#7050000
0#
#7060000
b101100001 S
1#
#7070000
0#
#7080000
b101100010 S
1#
#7090000
0#
#7100000
b101100011 S
1#
#7110000
0#
#7120000
b101100100 S
1#
#7130000
0#
#7140000
b101100101 S
1#
#7150000
0#
#7160000
b101100110 S
1#
#7170000
0#
#7180000
b101100111 S
1#
#7190000
0#
#7200000
b101101000 S
1#
#7210000
0#
#7220000
b101101001 S
1#
#7230000
0#
#7240000
b101101010 S
1#
#7250000
0#
#7260000
b101101011 S
1#
#7270000
0#
#7280000
b101101100 S
1#
#7290000
0#
#7300000
b101101101 S
1#
#7310000
0#
#7320000
b101101110 S
1#
#7330000
0#
#7340000
b101101111 S
1#
#7350000
0#
#7360000
b101110000 S
1#
#7370000
0#
#7380000
b101110001 S
1#
#7390000
0#
#7400000
b101110010 S
1#
#7410000
0#
#7420000
b101110011 S
1#
#7430000
0#
#7440000
b101110100 S
1#
#7450000
0#
#7460000
b101110101 S
1#
#7470000
0#
#7480000
b101110110 S
1#
#7490000
0#
#7500000
b101110111 S
1#
#7510000
0#
#7520000
b101111000 S
1#
#7530000
0#
#7540000
b101111001 S
1#
#7550000
0#
#7560000
b101111010 S
1#
#7570000
0#
#7580000
b101111011 S
1#
#7590000
0#
#7600000
b101111100 S
1#
#7610000
0#
